<?xml version="1.0" encoding="UTF-8"?>
<res>
<data><date>2017-03-04</date><num>786</num></data>
<data><date>2017-03-04</date><num>439</num></data>
<data><date>2017-03-04</date><num>229</num></data>
<data><date>2017-03-04</date><num>396</num></data>
<data><date>2017-03-04</date><num>462</num></data>
<data><date>2017-03-04</date><num>236</num></data>
<data><date>2017-03-04</date><num>637</num></data>
<data><date>2017-03-04</date><num>464</num></data>
<data><date>2017-03-04</date><num>985</num></data>
<data><date>2017-03-04</date><num>821</num></data>
<data><date>2017-03-04</date><num>347</num></data>
<data><date>2017-03-04</date><num>271</num></data>
<data><date>2017-03-04</date><num>353</num></data>
<data><date>2017-03-04</date><num>615</num></data>
<data><date>2017-03-04</date><num>436</num></data>
<data><date>2017-03-04</date><num>54</num></data>
<data><date>2017-03-04</date><num>613</num></data>
<data><date>2017-03-04</date><num>339</num></data>
<data><date>2017-03-04</date><num>562</num></data>
<data><date>2017-03-04</date><num>663</num></data>
<data><date>2017-03-04</date><num>249</num></data>
<data><date>2017-03-04</date><num>797</num></data>
<data><date>2017-03-04</date><num>29</num></data>
<data><date>2017-03-04</date><num>102</num></data>
<data><date>2017-03-04</date><num>599</num></data>
<data><date>2017-03-04</date><num>839</num></data>
<data><date>2017-03-04</date><num>579</num></data>
<data><date>2017-03-04</date><num>385</num></data>
<data><date>2017-03-04</date><num>15</num></data>
<data><date>2017-03-04</date><num>689</num></data>
<data><date>2017-03-04</date><num>513</num></data>
<data><date>2017-03-04</date><num>800</num></data>
<data><date>2017-03-04</date><num>127</num></data>
<data><date>2017-03-04</date><num>741</num></data>
<data><date>2017-03-04</date><num>196</num></data>
<data><date>2017-03-04</date><num>589</num></data>
<data><date>2017-03-04</date><num>977</num></data>
<data><date>2017-03-04</date><num>832</num></data>
<data><date>2017-03-04</date><num>52</num></data>
<data><date>2017-03-04</date><num>961</num></data>
<data><date>2017-03-04</date><num>653</num></data>
<data><date>2017-03-04</date><num>399</num></data>
<data><date>2017-03-04</date><num>231</num></data>
<data><date>2017-03-04</date><num>5</num></data>
<data><date>2017-03-04</date><num>14</num></data>
<data><date>2017-03-04</date><num>666</num></data>
<data><date>2017-03-04</date><num>58</num></data>
<data><date>2017-03-04</date><num>627</num></data>
<data><date>2017-03-04</date><num>5</num></data>
<data><date>2017-03-04</date><num>620</num></data>
<data><date>2017-03-04</date><num>289</num></data>
<data><date>2017-03-04</date><num>253</num></data>
<data><date>2017-03-04</date><num>416</num></data>
<data><date>2017-03-04</date><num>317</num></data>
<data><date>2017-03-04</date><num>354</num></data>
<data><date>2017-03-04</date><num>15</num></data>
<data><date>2017-03-04</date><num>156</num></data>
<data><date>2017-03-04</date><num>933</num></data>
<data><date>2017-03-04</date><num>399</num></data>
<data><date>2017-03-04</date><num>170</num></data>
<data><date>2017-03-04</date><num>621</num></data>
<data><date>2017-03-04</date><num>912</num></data>
<data><date>2017-03-04</date><num>970</num></data>
<data><date>2017-03-04</date><num>747</num></data>
<data><date>2017-03-04</date><num>653</num></data>
<data><date>2017-03-04</date><num>166</num></data>
<data><date>2017-03-04</date><num>336</num></data>
<data><date>2017-03-04</date><num>629</num></data>
<data><date>2017-03-04</date><num>997</num></data>
<data><date>2017-03-04</date><num>388</num></data>
<data><date>2017-03-04</date><num>590</num></data>
<data><date>2017-03-04</date><num>650</num></data>
<data><date>2017-03-04</date><num>787</num></data>
<data><date>2017-03-04</date><num>820</num></data>
<data><date>2017-03-04</date><num>655</num></data>
<data><date>2017-03-04</date><num>800</num></data>
<data><date>2017-03-04</date><num>486</num></data>
<data><date>2017-03-04</date><num>713</num></data>
<data><date>2017-03-04</date><num>426</num></data>
<data><date>2017-03-04</date><num>490</num></data>
<data><date>2017-03-04</date><num>332</num></data>
<data><date>2017-03-04</date><num>715</num></data>
<data><date>2017-03-04</date><num>743</num></data>
<data><date>2017-03-04</date><num>748</num></data>
<data><date>2017-03-04</date><num>32</num></data>
<data><date>2017-03-04</date><num>97</num></data>
<data><date>2017-03-04</date><num>762</num></data>
<data><date>2017-03-04</date><num>187</num></data>
<data><date>2017-03-04</date><num>29</num></data>
<data><date>2017-03-04</date><num>161</num></data>
<data><date>2017-03-04</date><num>356</num></data>
<data><date>2017-03-04</date><num>650</num></data>
<data><date>2017-03-04</date><num>73</num></data>
<data><date>2017-03-04</date><num>326</num></data>
<data><date>2017-03-04</date><num>397</num></data>
<data><date>2017-03-04</date><num>725</num></data>
<data><date>2017-03-04</date><num>491</num></data>
<data><date>2017-03-04</date><num>732</num></data>
<data><date>2017-03-04</date><num>354</num></data>
<data><date>2017-03-04</date><num>488</num></data>
<data><date>2017-03-04</date><num>119</num></data>
<data><date>2017-03-04</date><num>943</num></data>
<data><date>2017-03-04</date><num>138</num></data>
<data><date>2017-03-04</date><num>906</num></data>
<data><date>2017-03-04</date><num>763</num></data>
<data><date>2017-03-04</date><num>792</num></data>
<data><date>2017-03-04</date><num>705</num></data>
<data><date>2017-03-04</date><num>248</num></data>
<data><date>2017-03-04</date><num>504</num></data>
<data><date>2017-03-04</date><num>130</num></data>
<data><date>2017-03-04</date><num>738</num></data>
<data><date>2017-03-04</date><num>836</num></data>
<data><date>2017-03-04</date><num>845</num></data>
<data><date>2017-03-04</date><num>481</num></data>
<data><date>2017-03-04</date><num>583</num></data>
<data><date>2017-03-04</date><num>876</num></data>
<data><date>2017-03-04</date><num>577</num></data>
<data><date>2017-03-04</date><num>345</num></data>
<data><date>2017-03-04</date><num>62</num></data>
<data><date>2017-03-04</date><num>606</num></data>
<data><date>2017-03-04</date><num>506</num></data>
<data><date>2017-03-04</date><num>418</num></data>
<data><date>2017-03-04</date><num>255</num></data>
<data><date>2017-03-04</date><num>578</num></data>
<data><date>2017-03-04</date><num>744</num></data>
<data><date>2017-03-04</date><num>651</num></data>
<data><date>2017-03-04</date><num>303</num></data>
<data><date>2017-03-04</date><num>234</num></data>
<data><date>2017-03-04</date><num>383</num></data>
<data><date>2017-03-04</date><num>657</num></data>
<data><date>2017-03-04</date><num>722</num></data>
<data><date>2017-03-04</date><num>502</num></data>
<data><date>2017-03-04</date><num>599</num></data>
<data><date>2017-03-04</date><num>859</num></data>
<data><date>2017-03-04</date><num>407</num></data>
<data><date>2017-03-04</date><num>361</num></data>
<data><date>2017-03-04</date><num>650</num></data>
<data><date>2017-03-04</date><num>111</num></data>
<data><date>2017-03-04</date><num>609</num></data>
<data><date>2017-03-04</date><num>154</num></data>
<data><date>2017-03-04</date><num>241</num></data>
<data><date>2017-03-04</date><num>347</num></data>
<data><date>2017-03-04</date><num>989</num></data>
<data><date>2017-03-04</date><num>85</num></data>
<data><date>2017-03-04</date><num>828</num></data>
<data><date>2017-03-04</date><num>571</num></data>
<data><date>2017-03-04</date><num>961</num></data>
<data><date>2017-03-04</date><num>405</num></data>
<data><date>2017-03-04</date><num>916</num></data>
<data><date>2017-03-04</date><num>22</num></data>
<data><date>2017-03-04</date><num>10</num></data>
<data><date>2017-03-04</date><num>421</num></data>
<data><date>2017-03-04</date><num>440</num></data>
<data><date>2017-03-04</date><num>265</num></data>
<data><date>2017-03-04</date><num>998</num></data>
<data><date>2017-03-04</date><num>183</num></data>
<data><date>2017-03-04</date><num>915</num></data>
<data><date>2017-03-04</date><num>301</num></data>
<data><date>2017-03-04</date><num>416</num></data>
<data><date>2017-03-04</date><num>298</num></data>
<data><date>2017-03-04</date><num>957</num></data>
<data><date>2017-03-04</date><num>138</num></data>
<data><date>2017-03-04</date><num>799</num></data>
<data><date>2017-03-04</date><num>555</num></data>
<data><date>2017-03-04</date><num>996</num></data>
<data><date>2017-03-04</date><num>205</num></data>
<data><date>2017-03-04</date><num>916</num></data>
<data><date>2017-03-04</date><num>646</num></data>
<data><date>2017-03-04</date><num>316</num></data>
<data><date>2017-03-04</date><num>525</num></data>
<data><date>2017-03-04</date><num>799</num></data>
<data><date>2017-03-04</date><num>556</num></data>
<data><date>2017-03-04</date><num>872</num></data>
<data><date>2017-03-04</date><num>787</num></data>
<data><date>2017-03-04</date><num>641</num></data>
<data><date>2017-03-04</date><num>699</num></data>
<data><date>2017-03-04</date><num>358</num></data>
<data><date>2017-03-04</date><num>601</num></data>
<data><date>2017-03-04</date><num>104</num></data>
<data><date>2017-03-04</date><num>273</num></data>
<data><date>2017-03-04</date><num>623</num></data>
<data><date>2017-03-04</date><num>113</num></data>
<data><date>2017-03-04</date><num>693</num></data>
<data><date>2017-03-04</date><num>62</num></data>
<data><date>2017-03-04</date><num>377</num></data>
<data><date>2017-03-04</date><num>691</num></data>
<data><date>2017-03-04</date><num>244</num></data>
<data><date>2017-03-04</date><num>292</num></data>
<data><date>2017-03-04</date><num>991</num></data>
<data><date>2017-03-04</date><num>660</num></data>
<data><date>2017-03-04</date><num>589</num></data>
<data><date>2017-03-04</date><num>948</num></data>
<data><date>2017-03-04</date><num>798</num></data>
<data><date>2017-03-04</date><num>388</num></data>
<data><date>2017-03-04</date><num>503</num></data>
<data><date>2017-03-04</date><num>793</num></data>
<data><date>2017-03-04</date><num>592</num></data>
<data><date>2017-03-04</date><num>418</num></data>
<data><date>2017-03-04</date><num>438</num></data>
<data><date>2017-03-04</date><num>908</num></data>
<data><date>2017-03-04</date><num>943</num></data>
<data><date>2017-03-04</date><num>237</num></data>
<data><date>2017-03-04</date><num>464</num></data>
<data><date>2017-03-04</date><num>815</num></data>
<data><date>2017-03-04</date><num>23</num></data>
<data><date>2017-03-04</date><num>104</num></data>
<data><date>2017-03-04</date><num>514</num></data>
<data><date>2017-03-04</date><num>381</num></data>
<data><date>2017-03-04</date><num>705</num></data>
<data><date>2017-03-04</date><num>617</num></data>
<data><date>2017-03-04</date><num>654</num></data>
<data><date>2017-03-04</date><num>327</num></data>
<data><date>2017-03-04</date><num>730</num></data>
<data><date>2017-03-04</date><num>347</num></data>
<data><date>2017-03-04</date><num>389</num></data>
<data><date>2017-03-04</date><num>106</num></data>
<data><date>2017-03-04</date><num>37</num></data>
<data><date>2017-03-04</date><num>632</num></data>
<data><date>2017-03-04</date><num>398</num></data>
<data><date>2017-03-04</date><num>28</num></data>
<data><date>2017-03-04</date><num>292</num></data>
<data><date>2017-03-04</date><num>987</num></data>
<data><date>2017-03-04</date><num>975</num></data>
<data><date>2017-03-04</date><num>89</num></data>
<data><date>2017-03-04</date><num>374</num></data>
<data><date>2017-03-04</date><num>478</num></data>
<data><date>2017-03-04</date><num>882</num></data>
<data><date>2017-03-04</date><num>966</num></data>
<data><date>2017-03-04</date><num>896</num></data>
<data><date>2017-03-04</date><num>320</num></data>
<data><date>2017-03-04</date><num>873</num></data>
<data><date>2017-03-04</date><num>838</num></data>
<data><date>2017-03-04</date><num>556</num></data>
<data><date>2017-03-04</date><num>336</num></data>
<data><date>2017-03-04</date><num>653</num></data>
<data><date>2017-03-04</date><num>579</num></data>
<data><date>2017-03-04</date><num>440</num></data>
<data><date>2017-03-04</date><num>166</num></data>
<data><date>2017-03-04</date><num>959</num></data>
<data><date>2017-03-04</date><num>144</num></data>
<data><date>2017-03-04</date><num>783</num></data>
<data><date>2017-03-04</date><num>613</num></data>
<data><date>2017-03-04</date><num>471</num></data>
<data><date>2017-03-04</date><num>512</num></data>
<data><date>2017-03-04</date><num>959</num></data>
<data><date>2017-03-04</date><num>859</num></data>
<data><date>2017-03-04</date><num>618</num></data>
<data><date>2017-03-04</date><num>995</num></data>
<data><date>2017-03-04</date><num>491</num></data>
<data><date>2017-03-04</date><num>16</num></data>
<data><date>2017-03-04</date><num>23</num></data>
<data><date>2017-03-04</date><num>783</num></data>
<data><date>2017-03-04</date><num>2</num></data>
<data><date>2017-03-04</date><num>998</num></data>
<data><date>2017-03-04</date><num>871</num></data>
<data><date>2017-03-04</date><num>376</num></data>
<data><date>2017-03-04</date><num>475</num></data>
<data><date>2017-03-04</date><num>753</num></data>
<data><date>2017-03-04</date><num>342</num></data>
<data><date>2017-03-04</date><num>370</num></data>
<data><date>2017-03-04</date><num>72</num></data>
<data><date>2017-03-04</date><num>215</num></data>
<data><date>2017-03-04</date><num>208</num></data>
<data><date>2017-03-04</date><num>627</num></data>
<data><date>2017-03-04</date><num>551</num></data>
<data><date>2017-03-04</date><num>861</num></data>
<data><date>2017-03-04</date><num>206</num></data>
<data><date>2017-03-04</date><num>990</num></data>
<data><date>2017-03-04</date><num>27</num></data>
<data><date>2017-03-04</date><num>165</num></data>
<data><date>2017-03-04</date><num>134</num></data>
<data><date>2017-03-04</date><num>809</num></data>
<data><date>2017-03-04</date><num>777</num></data>
<data><date>2017-03-04</date><num>604</num></data>
<data><date>2017-03-04</date><num>321</num></data>
<data><date>2017-03-04</date><num>735</num></data>
<data><date>2017-03-04</date><num>463</num></data>
<data><date>2017-03-04</date><num>939</num></data>
<data><date>2017-03-04</date><num>730</num></data>
<data><date>2017-03-04</date><num>953</num></data>
<data><date>2017-03-04</date><num>954</num></data>
<data><date>2017-03-04</date><num>753</num></data>
<data><date>2017-03-04</date><num>735</num></data>
<data><date>2017-03-04</date><num>956</num></data>
<data><date>2017-03-04</date><num>750</num></data>
<data><date>2017-03-04</date><num>606</num></data>
<data><date>2017-03-04</date><num>331</num></data>
<data><date>2017-03-04</date><num>225</num></data>
<data><date>2017-03-04</date><num>358</num></data>
<data><date>2017-03-04</date><num>673</num></data>
<data><date>2017-03-04</date><num>595</num></data>
<data><date>2017-03-04</date><num>430</num></data>
<data><date>2017-03-04</date><num>887</num></data>
<data><date>2017-03-04</date><num>803</num></data>
<data><date>2017-03-04</date><num>57</num></data>
<data><date>2017-03-04</date><num>437</num></data>
<data><date>2017-03-04</date><num>663</num></data>
<data><date>2017-03-04</date><num>262</num></data>
<data><date>2017-03-04</date><num>427</num></data>
<data><date>2017-03-04</date><num>689</num></data>
<data><date>2017-03-04</date><num>426</num></data>
<data><date>2017-03-04</date><num>561</num></data>
<data><date>2017-03-04</date><num>497</num></data>
<data><date>2017-03-04</date><num>202</num></data>
<data><date>2017-03-04</date><num>165</num></data>
<data><date>2017-03-04</date><num>818</num></data>
<data><date>2017-03-04</date><num>937</num></data>
<data><date>2017-03-04</date><num>627</num></data>
<data><date>2017-03-04</date><num>756</num></data>
<data><date>2017-03-04</date><num>666</num></data>
<data><date>2017-03-04</date><num>580</num></data>
<data><date>2017-03-04</date><num>709</num></data>
<data><date>2017-03-04</date><num>418</num></data>
<data><date>2017-03-04</date><num>314</num></data>
<data><date>2017-03-04</date><num>664</num></data>
<data><date>2017-03-04</date><num>168</num></data>
<data><date>2017-03-04</date><num>920</num></data>
<data><date>2017-03-04</date><num>995</num></data>
<data><date>2017-03-04</date><num>393</num></data>
<data><date>2017-03-04</date><num>278</num></data>
<data><date>2017-03-04</date><num>667</num></data>
<data><date>2017-03-04</date><num>987</num></data>
<data><date>2017-03-04</date><num>707</num></data>
<data><date>2017-03-04</date><num>554</num></data>
<data><date>2017-03-04</date><num>789</num></data>
<data><date>2017-03-04</date><num>763</num></data>
<data><date>2017-03-04</date><num>991</num></data>
<data><date>2017-03-04</date><num>451</num></data>
<data><date>2017-03-04</date><num>25</num></data>
<data><date>2017-03-04</date><num>418</num></data>
<data><date>2017-03-04</date><num>140</num></data>
<data><date>2017-03-04</date><num>450</num></data>
<data><date>2017-03-04</date><num>978</num></data>
<data><date>2017-03-04</date><num>637</num></data>
<data><date>2017-03-04</date><num>652</num></data>
<data><date>2017-03-04</date><num>143</num></data>
<data><date>2017-03-04</date><num>454</num></data>
<data><date>2017-03-04</date><num>588</num></data>
<data><date>2017-03-04</date><num>769</num></data>
<data><date>2017-03-04</date><num>209</num></data>
<data><date>2017-03-04</date><num>254</num></data>
<data><date>2017-03-04</date><num>349</num></data>
<data><date>2017-03-04</date><num>918</num></data>
<data><date>2017-03-04</date><num>672</num></data>
<data><date>2017-03-04</date><num>662</num></data>
<data><date>2017-03-04</date><num>582</num></data>
<data><date>2017-03-04</date><num>839</num></data>
<data><date>2017-03-04</date><num>581</num></data>
<data><date>2017-03-04</date><num>576</num></data>
<data><date>2017-03-04</date><num>231</num></data>
<data><date>2017-03-04</date><num>858</num></data>
<data><date>2017-03-04</date><num>243</num></data>
<data><date>2017-03-04</date><num>218</num></data>
<data><date>2017-03-04</date><num>565</num></data>
<data><date>2017-03-04</date><num>796</num></data>
<data><date>2017-03-04</date><num>7</num></data>
<data><date>2017-03-04</date><num>327</num></data>
<data><date>2017-03-04</date><num>786</num></data>
<data><date>2017-03-04</date><num>458</num></data>
<data><date>2017-03-04</date><num>351</num></data>
<data><date>2017-03-04</date><num>203</num></data>
<data><date>2017-03-04</date><num>597</num></data>
<data><date>2017-03-04</date><num>801</num></data>
<data><date>2017-03-04</date><num>181</num></data>
<data><date>2017-03-04</date><num>233</num></data>
<data><date>2017-03-04</date><num>453</num></data>
<data><date>2017-03-04</date><num>323</num></data>
<data><date>2017-03-04</date><num>687</num></data>
<data><date>2017-03-04</date><num>40</num></data>
<data><date>2017-03-04</date><num>92</num></data>
<data><date>2017-03-04</date><num>896</num></data>
<data><date>2017-03-04</date><num>294</num></data>
<data><date>2017-03-04</date><num>440</num></data>
<data><date>2017-03-04</date><num>813</num></data>
<data><date>2017-03-04</date><num>965</num></data>
<data><date>2017-03-04</date><num>102</num></data>
<data><date>2017-03-04</date><num>394</num></data>
<data><date>2017-03-04</date><num>804</num></data>
<data><date>2017-03-04</date><num>683</num></data>
<data><date>2017-03-04</date><num>969</num></data>
<data><date>2017-03-04</date><num>35</num></data>
<data><date>2017-03-04</date><num>541</num></data>
<data><date>2017-03-04</date><num>212</num></data>
<data><date>2017-03-04</date><num>253</num></data>
<data><date>2017-03-04</date><num>105</num></data>
<data><date>2017-03-04</date><num>7</num></data>
<data><date>2017-03-04</date><num>259</num></data>
<data><date>2017-03-04</date><num>432</num></data>
<data><date>2017-03-04</date><num>793</num></data>
<data><date>2017-03-04</date><num>716</num></data>
<data><date>2017-03-04</date><num>783</num></data>
<data><date>2017-03-04</date><num>996</num></data>
<data><date>2017-03-04</date><num>313</num></data>
<data><date>2017-03-04</date><num>583</num></data>
<data><date>2017-03-04</date><num>177</num></data>
<data><date>2017-03-04</date><num>546</num></data>
<data><date>2017-03-04</date><num>36</num></data>
<data><date>2017-03-04</date><num>500</num></data>
<data><date>2017-03-04</date><num>232</num></data>
<data><date>2017-03-04</date><num>76</num></data>
<data><date>2017-03-04</date><num>591</num></data>
<data><date>2017-03-04</date><num>127</num></data>
<data><date>2017-03-04</date><num>369</num></data>
<data><date>2017-03-04</date><num>31</num></data>
<data><date>2017-03-04</date><num>940</num></data>
<data><date>2017-03-04</date><num>334</num></data>
<data><date>2017-03-04</date><num>133</num></data>
<data><date>2017-03-04</date><num>333</num></data>
<data><date>2017-03-04</date><num>137</num></data>
<data><date>2017-03-04</date><num>815</num></data>
<data><date>2017-03-04</date><num>302</num></data>
<data><date>2017-03-04</date><num>171</num></data>
<data><date>2017-03-04</date><num>355</num></data>
<data><date>2017-03-04</date><num>513</num></data>
<data><date>2017-03-04</date><num>423</num></data>
<data><date>2017-03-04</date><num>460</num></data>
<data><date>2017-03-04</date><num>520</num></data>
<data><date>2017-03-04</date><num>682</num></data>
<data><date>2017-03-04</date><num>891</num></data>
<data><date>2017-03-04</date><num>312</num></data>
<data><date>2017-03-04</date><num>398</num></data>
<data><date>2017-03-04</date><num>674</num></data>
<data><date>2017-03-04</date><num>308</num></data>
<data><date>2017-03-04</date><num>710</num></data>
<data><date>2017-03-04</date><num>256</num></data>
<data><date>2017-03-04</date><num>484</num></data>
<data><date>2017-03-04</date><num>255</num></data>
<data><date>2017-03-04</date><num>292</num></data>
<data><date>2017-03-04</date><num>983</num></data>
<data><date>2017-03-04</date><num>487</num></data>
<data><date>2017-03-04</date><num>367</num></data>
<data><date>2017-03-04</date><num>574</num></data>
<data><date>2017-03-04</date><num>614</num></data>
<data><date>2017-03-04</date><num>735</num></data>
<data><date>2017-03-04</date><num>604</num></data>
<data><date>2017-03-04</date><num>553</num></data>
<data><date>2017-03-04</date><num>68</num></data>
<data><date>2017-03-04</date><num>737</num></data>
<data><date>2017-03-04</date><num>885</num></data>
<data><date>2017-03-04</date><num>205</num></data>
<data><date>2017-03-04</date><num>551</num></data>
<data><date>2017-03-04</date><num>186</num></data>
<data><date>2017-03-04</date><num>376</num></data>
<data><date>2017-03-04</date><num>906</num></data>
<data><date>2017-03-04</date><num>699</num></data>
<data><date>2017-03-04</date><num>799</num></data>
<data><date>2017-03-04</date><num>366</num></data>
<data><date>2017-03-04</date><num>218</num></data>
<data><date>2017-03-04</date><num>480</num></data>
<data><date>2017-03-04</date><num>256</num></data>
<data><date>2017-03-04</date><num>530</num></data>
<data><date>2017-03-04</date><num>877</num></data>
<data><date>2017-03-04</date><num>930</num></data>
<data><date>2017-03-04</date><num>837</num></data>
<data><date>2017-03-04</date><num>586</num></data>
<data><date>2017-03-04</date><num>186</num></data>
<data><date>2017-03-04</date><num>320</num></data>
<data><date>2017-03-04</date><num>841</num></data>
<data><date>2017-03-04</date><num>477</num></data>
<data><date>2017-03-04</date><num>302</num></data>
<data><date>2017-03-04</date><num>328</num></data>
<data><date>2017-03-04</date><num>843</num></data>
<data><date>2017-03-04</date><num>876</num></data>
<data><date>2017-03-04</date><num>941</num></data>
<data><date>2017-03-04</date><num>577</num></data>
<data><date>2017-03-04</date><num>479</num></data>
<data><date>2017-03-04</date><num>493</num></data>
<data><date>2017-03-04</date><num>645</num></data>
<data><date>2017-03-04</date><num>215</num></data>
<data><date>2017-03-04</date><num>377</num></data>
<data><date>2017-03-04</date><num>850</num></data>
<data><date>2017-03-04</date><num>766</num></data>
<data><date>2017-03-04</date><num>563</num></data>
<data><date>2017-03-04</date><num>225</num></data>
<data><date>2017-03-04</date><num>672</num></data>
<data><date>2017-03-04</date><num>262</num></data>
<data><date>2017-03-04</date><num>23</num></data>
<data><date>2017-03-04</date><num>37</num></data>
<data><date>2017-03-04</date><num>479</num></data>
<data><date>2017-03-04</date><num>502</num></data>
<data><date>2017-03-04</date><num>293</num></data>
<data><date>2017-03-04</date><num>9</num></data>
<data><date>2017-03-04</date><num>378</num></data>
<data><date>2017-03-04</date><num>222</num></data>
<data><date>2017-03-04</date><num>845</num></data>
<data><date>2017-03-04</date><num>964</num></data>
<data><date>2017-03-04</date><num>407</num></data>
<data><date>2017-03-04</date><num>165</num></data>
<data><date>2017-03-04</date><num>805</num></data>
<data><date>2017-03-04</date><num>883</num></data>
<data><date>2017-03-04</date><num>467</num></data>
<data><date>2017-03-04</date><num>132</num></data>
<data><date>2017-03-04</date><num>725</num></data>
<data><date>2017-03-04</date><num>342</num></data>
<data><date>2017-03-04</date><num>72</num></data>
<data><date>2017-03-04</date><num>302</num></data>
<data><date>2017-03-04</date><num>821</num></data>
<data><date>2017-03-04</date><num>564</num></data>
<data><date>2017-03-04</date><num>947</num></data>
<data><date>2017-03-04</date><num>36</num></data>
<data><date>2017-03-04</date><num>941</num></data>
<data><date>2017-03-04</date><num>796</num></data>
<data><date>2017-03-04</date><num>801</num></data>
<data><date>2017-03-04</date><num>504</num></data>
<data><date>2017-03-04</date><num>20</num></data>
<data><date>2017-03-04</date><num>472</num></data>
<data><date>2017-03-04</date><num>765</num></data>
<data><date>2017-03-04</date><num>42</num></data>
<data><date>2017-03-04</date><num>509</num></data>
<data><date>2017-03-04</date><num>244</num></data>
<data><date>2017-03-04</date><num>544</num></data>
<data><date>2017-03-04</date><num>801</num></data>
<data><date>2017-03-04</date><num>252</num></data>
<data><date>2017-03-04</date><num>922</num></data>
<data><date>2017-03-04</date><num>22</num></data>
<data><date>2017-03-04</date><num>97</num></data>
<data><date>2017-03-04</date><num>885</num></data>
<data><date>2017-03-04</date><num>429</num></data>
<data><date>2017-03-04</date><num>262</num></data>
<data><date>2017-03-04</date><num>690</num></data>
<data><date>2017-03-04</date><num>311</num></data>
<data><date>2017-03-04</date><num>728</num></data>
<data><date>2017-03-04</date><num>821</num></data>
<data><date>2017-03-04</date><num>36</num></data>
<data><date>2017-03-04</date><num>70</num></data>
<data><date>2017-03-04</date><num>893</num></data>
<data><date>2017-03-04</date><num>338</num></data>
<data><date>2017-03-04</date><num>890</num></data>
<data><date>2017-03-04</date><num>457</num></data>
<data><date>2017-03-04</date><num>284</num></data>
<data><date>2017-03-04</date><num>925</num></data>
<data><date>2017-03-04</date><num>398</num></data>
<data><date>2017-03-04</date><num>80</num></data>
<data><date>2017-03-04</date><num>726</num></data>
<data><date>2017-03-04</date><num>901</num></data>
<data><date>2017-03-04</date><num>100</num></data>
<data><date>2017-03-04</date><num>198</num></data>
<data><date>2017-03-04</date><num>666</num></data>
<data><date>2017-03-04</date><num>142</num></data>
<data><date>2017-03-04</date><num>706</num></data>
<data><date>2017-03-04</date><num>909</num></data>
<data><date>2017-03-04</date><num>685</num></data>
<data><date>2017-03-04</date><num>507</num></data>
<data><date>2017-03-04</date><num>161</num></data>
<data><date>2017-03-04</date><num>606</num></data>
<data><date>2017-03-04</date><num>528</num></data>
<data><date>2017-03-04</date><num>258</num></data>
<data><date>2017-03-04</date><num>491</num></data>
<data><date>2017-03-04</date><num>957</num></data>
<data><date>2017-03-04</date><num>519</num></data>
<data><date>2017-03-04</date><num>181</num></data>
<data><date>2017-03-04</date><num>267</num></data>
<data><date>2017-03-04</date><num>247</num></data>
<data><date>2017-03-04</date><num>2</num></data>
<data><date>2017-03-04</date><num>303</num></data>
<data><date>2017-03-04</date><num>316</num></data>
<data><date>2017-03-04</date><num>894</num></data>
<data><date>2017-03-04</date><num>640</num></data>
<data><date>2017-03-04</date><num>206</num></data>
<data><date>2017-03-04</date><num>351</num></data>
<data><date>2017-03-04</date><num>924</num></data>
<data><date>2017-03-04</date><num>130</num></data>
<data><date>2017-03-04</date><num>748</num></data>
<data><date>2017-03-04</date><num>4</num></data>
<data><date>2017-03-04</date><num>856</num></data>
<data><date>2017-03-04</date><num>648</num></data>
<data><date>2017-03-04</date><num>103</num></data>
<data><date>2017-03-04</date><num>53</num></data>
<data><date>2017-03-04</date><num>314</num></data>
<data><date>2017-03-04</date><num>244</num></data>
<data><date>2017-03-04</date><num>759</num></data>
<data><date>2017-03-04</date><num>222</num></data>
<data><date>2017-03-04</date><num>928</num></data>
<data><date>2017-03-04</date><num>265</num></data>
<data><date>2017-03-04</date><num>382</num></data>
<data><date>2017-03-04</date><num>534</num></data>
<data><date>2017-03-04</date><num>793</num></data>
<data><date>2017-03-04</date><num>639</num></data>
<data><date>2017-03-04</date><num>25</num></data>
<data><date>2017-03-04</date><num>749</num></data>
<data><date>2017-03-04</date><num>158</num></data>
<data><date>2017-03-04</date><num>205</num></data>
<data><date>2017-03-04</date><num>16</num></data>
<data><date>2017-03-04</date><num>404</num></data>
<data><date>2017-03-04</date><num>206</num></data>
<data><date>2017-03-04</date><num>319</num></data>
<data><date>2017-03-04</date><num>719</num></data>
<data><date>2017-03-04</date><num>100</num></data>
<data><date>2017-03-04</date><num>958</num></data>
<data><date>2017-03-04</date><num>924</num></data>
<data><date>2017-03-04</date><num>450</num></data>
<data><date>2017-03-04</date><num>882</num></data>
<data><date>2017-03-04</date><num>54</num></data>
<data><date>2017-03-04</date><num>198</num></data>
<data><date>2017-03-04</date><num>885</num></data>
<data><date>2017-03-04</date><num>910</num></data>
<data><date>2017-03-04</date><num>846</num></data>
<data><date>2017-03-04</date><num>987</num></data>
<data><date>2017-03-04</date><num>962</num></data>
<data><date>2017-03-04</date><num>159</num></data>
<data><date>2017-03-04</date><num>231</num></data>
<data><date>2017-03-04</date><num>721</num></data>
<data><date>2017-03-04</date><num>380</num></data>
<data><date>2017-03-04</date><num>159</num></data>
<data><date>2017-03-04</date><num>985</num></data>
<data><date>2017-03-04</date><num>762</num></data>
<data><date>2017-03-04</date><num>692</num></data>
<data><date>2017-03-04</date><num>778</num></data>
<data><date>2017-03-04</date><num>401</num></data>
<data><date>2017-03-04</date><num>717</num></data>
<data><date>2017-03-04</date><num>527</num></data>
<data><date>2017-03-04</date><num>558</num></data>
<data><date>2017-03-04</date><num>921</num></data>
<data><date>2017-03-04</date><num>542</num></data>
<data><date>2017-03-04</date><num>962</num></data>
<data><date>2017-03-04</date><num>127</num></data>
<data><date>2017-03-04</date><num>860</num></data>
<data><date>2017-03-04</date><num>680</num></data>
<data><date>2017-03-04</date><num>226</num></data>
<data><date>2017-03-04</date><num>818</num></data>
<data><date>2017-03-04</date><num>604</num></data>
<data><date>2017-03-04</date><num>676</num></data>
<data><date>2017-03-04</date><num>700</num></data>
<data><date>2017-03-04</date><num>658</num></data>
<data><date>2017-03-04</date><num>873</num></data>
<data><date>2017-03-04</date><num>584</num></data>
<data><date>2017-03-04</date><num>567</num></data>
<data><date>2017-03-04</date><num>718</num></data>
<data><date>2017-03-04</date><num>571</num></data>
<data><date>2017-03-04</date><num>529</num></data>
<data><date>2017-03-04</date><num>876</num></data>
<data><date>2017-03-04</date><num>801</num></data>
<data><date>2017-03-04</date><num>249</num></data>
<data><date>2017-03-04</date><num>256</num></data>
<data><date>2017-03-04</date><num>960</num></data>
<data><date>2017-03-04</date><num>234</num></data>
<data><date>2017-03-04</date><num>17</num></data>
<data><date>2017-03-04</date><num>651</num></data>
<data><date>2017-03-04</date><num>11</num></data>
<data><date>2017-03-04</date><num>418</num></data>
<data><date>2017-03-04</date><num>368</num></data>
<data><date>2017-03-04</date><num>537</num></data>
<data><date>2017-03-04</date><num>976</num></data>
<data><date>2017-03-04</date><num>288</num></data>
<data><date>2017-03-04</date><num>79</num></data>
<data><date>2017-03-04</date><num>937</num></data>
<data><date>2017-03-04</date><num>415</num></data>
<data><date>2017-03-04</date><num>939</num></data>
<data><date>2017-03-04</date><num>617</num></data>
<data><date>2017-03-04</date><num>641</num></data>
<data><date>2017-03-04</date><num>757</num></data>
<data><date>2017-03-04</date><num>220</num></data>
<data><date>2017-03-04</date><num>316</num></data>
<data><date>2017-03-04</date><num>456</num></data>
<data><date>2017-03-04</date><num>878</num></data>
<data><date>2017-03-04</date><num>189</num></data>
<data><date>2017-03-04</date><num>40</num></data>
<data><date>2017-03-04</date><num>444</num></data>
<data><date>2017-03-04</date><num>906</num></data>
<data><date>2017-03-04</date><num>610</num></data>
<data><date>2017-03-04</date><num>972</num></data>
<data><date>2017-03-04</date><num>782</num></data>
<data><date>2017-03-04</date><num>411</num></data>
<data><date>2017-03-04</date><num>221</num></data>
<data><date>2017-03-04</date><num>37</num></data>
<data><date>2017-03-04</date><num>371</num></data>
<data><date>2017-03-04</date><num>454</num></data>
<data><date>2017-03-04</date><num>54</num></data>
<data><date>2017-03-04</date><num>22</num></data>
<data><date>2017-03-04</date><num>464</num></data>
<data><date>2017-03-04</date><num>472</num></data>
<data><date>2017-03-04</date><num>389</num></data>
<data><date>2017-03-04</date><num>1</num></data>
<data><date>2017-03-04</date><num>447</num></data>
<data><date>2017-03-04</date><num>677</num></data>
<data><date>2017-03-04</date><num>80</num></data>
<data><date>2017-03-04</date><num>384</num></data>
<data><date>2017-03-04</date><num>91</num></data>
<data><date>2017-03-04</date><num>18</num></data>
<data><date>2017-03-04</date><num>1000</num></data>
<data><date>2017-03-04</date><num>731</num></data>
<data><date>2017-03-04</date><num>774</num></data>
<data><date>2017-03-04</date><num>220</num></data>
<data><date>2017-03-04</date><num>47</num></data>
<data><date>2017-03-04</date><num>229</num></data>
<data><date>2017-03-04</date><num>97</num></data>
<data><date>2017-03-04</date><num>236</num></data>
<data><date>2017-03-04</date><num>268</num></data>
<data><date>2017-03-04</date><num>540</num></data>
<data><date>2017-03-04</date><num>141</num></data>
<data><date>2017-03-04</date><num>878</num></data>
<data><date>2017-03-04</date><num>511</num></data>
<data><date>2017-03-04</date><num>923</num></data>
<data><date>2017-03-04</date><num>289</num></data>
<data><date>2017-03-04</date><num>732</num></data>
<data><date>2017-03-04</date><num>960</num></data>
<data><date>2017-03-04</date><num>659</num></data>
<data><date>2017-03-04</date><num>185</num></data>
<data><date>2017-03-04</date><num>14</num></data>
<data><date>2017-03-04</date><num>680</num></data>
<data><date>2017-03-04</date><num>649</num></data>
<data><date>2017-03-04</date><num>485</num></data>
<data><date>2017-03-04</date><num>68</num></data>
<data><date>2017-03-04</date><num>650</num></data>
<data><date>2017-03-04</date><num>932</num></data>
<data><date>2017-03-04</date><num>745</num></data>
<data><date>2017-03-04</date><num>729</num></data>
<data><date>2017-03-04</date><num>315</num></data>
<data><date>2017-03-04</date><num>835</num></data>
<data><date>2017-03-04</date><num>746</num></data>
<data><date>2017-03-04</date><num>314</num></data>
<data><date>2017-03-04</date><num>566</num></data>
<data><date>2017-03-04</date><num>520</num></data>
<data><date>2017-03-04</date><num>533</num></data>
<data><date>2017-03-04</date><num>613</num></data>
<data><date>2017-03-04</date><num>748</num></data>
<data><date>2017-03-04</date><num>629</num></data>
<data><date>2017-03-04</date><num>848</num></data>
<data><date>2017-03-04</date><num>16</num></data>
<data><date>2017-03-04</date><num>169</num></data>
<data><date>2017-03-04</date><num>989</num></data>
<data><date>2017-03-04</date><num>894</num></data>
<data><date>2017-03-04</date><num>680</num></data>
<data><date>2017-03-04</date><num>911</num></data>
<data><date>2017-03-04</date><num>182</num></data>
<data><date>2017-03-04</date><num>411</num></data>
<data><date>2017-03-04</date><num>870</num></data>
<data><date>2017-03-04</date><num>841</num></data>
<data><date>2017-03-04</date><num>595</num></data>
<data><date>2017-03-04</date><num>884</num></data>
<data><date>2017-03-04</date><num>521</num></data>
<data><date>2017-03-04</date><num>243</num></data>
<data><date>2017-03-04</date><num>368</num></data>
<data><date>2017-03-04</date><num>589</num></data>
<data><date>2017-03-04</date><num>893</num></data>
<data><date>2017-03-04</date><num>299</num></data>
<data><date>2017-03-04</date><num>333</num></data>
<data><date>2017-03-04</date><num>621</num></data>
<data><date>2017-03-04</date><num>613</num></data>
<data><date>2017-03-04</date><num>167</num></data>
<data><date>2017-03-04</date><num>366</num></data>
<data><date>2017-03-04</date><num>927</num></data>
<data><date>2017-03-04</date><num>733</num></data>
<data><date>2017-03-04</date><num>885</num></data>
<data><date>2017-03-04</date><num>460</num></data>
<data><date>2017-03-04</date><num>345</num></data>
<data><date>2017-03-04</date><num>633</num></data>
<data><date>2017-03-04</date><num>88</num></data>
<data><date>2017-03-04</date><num>192</num></data>
<data><date>2017-03-04</date><num>649</num></data>
<data><date>2017-03-04</date><num>257</num></data>
<data><date>2017-03-04</date><num>181</num></data>
<data><date>2017-03-04</date><num>542</num></data>
<data><date>2017-03-04</date><num>936</num></data>
<data><date>2017-03-04</date><num>91</num></data>
<data><date>2017-03-04</date><num>724</num></data>
<data><date>2017-03-04</date><num>346</num></data>
<data><date>2017-03-04</date><num>961</num></data>
<data><date>2017-03-04</date><num>564</num></data>
<data><date>2017-03-04</date><num>941</num></data>
<data><date>2017-03-04</date><num>844</num></data>
<data><date>2017-03-04</date><num>85</num></data>
<data><date>2017-03-04</date><num>184</num></data>
<data><date>2017-03-04</date><num>212</num></data>
<data><date>2017-03-04</date><num>673</num></data>
<data><date>2017-03-04</date><num>76</num></data>
<data><date>2017-03-04</date><num>510</num></data>
<data><date>2017-03-04</date><num>5</num></data>
<data><date>2017-03-04</date><num>696</num></data>
<data><date>2017-03-04</date><num>123</num></data>
<data><date>2017-03-04</date><num>172</num></data>
<data><date>2017-03-04</date><num>62</num></data>
<data><date>2017-03-04</date><num>50</num></data>
<data><date>2017-03-04</date><num>904</num></data>
<data><date>2017-03-04</date><num>947</num></data>
<data><date>2017-03-04</date><num>509</num></data>
<data><date>2017-03-04</date><num>249</num></data>
<data><date>2017-03-04</date><num>579</num></data>
<data><date>2017-03-04</date><num>597</num></data>
<data><date>2017-03-04</date><num>440</num></data>
<data><date>2017-03-04</date><num>227</num></data>
<data><date>2017-03-04</date><num>853</num></data>
<data><date>2017-03-04</date><num>620</num></data>
<data><date>2017-03-04</date><num>769</num></data>
<data><date>2017-03-04</date><num>788</num></data>
<data><date>2017-03-04</date><num>711</num></data>
<data><date>2017-03-04</date><num>492</num></data>
<data><date>2017-03-04</date><num>134</num></data>
<data><date>2017-03-04</date><num>672</num></data>
<data><date>2017-03-04</date><num>56</num></data>
<data><date>2017-03-04</date><num>74</num></data>
<data><date>2017-03-04</date><num>515</num></data>
<data><date>2017-03-04</date><num>140</num></data>
<data><date>2017-03-04</date><num>257</num></data>
<data><date>2017-03-04</date><num>726</num></data>
<data><date>2017-03-04</date><num>812</num></data>
<data><date>2017-03-04</date><num>332</num></data>
<data><date>2017-03-04</date><num>236</num></data>
<data><date>2017-03-04</date><num>817</num></data>
<data><date>2017-03-04</date><num>28</num></data>
<data><date>2017-03-04</date><num>359</num></data>
<data><date>2017-03-04</date><num>988</num></data>
<data><date>2017-03-04</date><num>89</num></data>
<data><date>2017-03-04</date><num>408</num></data>
<data><date>2017-03-04</date><num>891</num></data>
<data><date>2017-03-04</date><num>35</num></data>
<data><date>2017-03-04</date><num>917</num></data>
<data><date>2017-03-04</date><num>139</num></data>
<data><date>2017-03-04</date><num>614</num></data>
<data><date>2017-03-04</date><num>513</num></data>
<data><date>2017-03-04</date><num>579</num></data>
<data><date>2017-03-04</date><num>841</num></data>
<data><date>2017-03-04</date><num>366</num></data>
<data><date>2017-03-04</date><num>199</num></data>
<data><date>2017-03-04</date><num>609</num></data>
<data><date>2017-03-04</date><num>153</num></data>
<data><date>2017-03-04</date><num>909</num></data>
<data><date>2017-03-04</date><num>101</num></data>
<data><date>2017-03-04</date><num>287</num></data>
<data><date>2017-03-04</date><num>581</num></data>
<data><date>2017-03-04</date><num>156</num></data>
<data><date>2017-03-04</date><num>361</num></data>
<data><date>2017-03-04</date><num>95</num></data>
<data><date>2017-03-04</date><num>296</num></data>
<data><date>2017-03-04</date><num>617</num></data>
<data><date>2017-03-04</date><num>821</num></data>
<data><date>2017-03-04</date><num>107</num></data>
<data><date>2017-03-04</date><num>949</num></data>
<data><date>2017-03-04</date><num>56</num></data>
<data><date>2017-03-04</date><num>923</num></data>
<data><date>2017-03-04</date><num>977</num></data>
<data><date>2017-03-04</date><num>415</num></data>
<data><date>2017-03-04</date><num>911</num></data>
<data><date>2017-03-04</date><num>65</num></data>
<data><date>2017-03-04</date><num>822</num></data>
<data><date>2017-03-04</date><num>801</num></data>
<data><date>2017-03-04</date><num>100</num></data>
<data><date>2017-03-04</date><num>738</num></data>
<data><date>2017-03-04</date><num>940</num></data>
<data><date>2017-03-04</date><num>714</num></data>
<data><date>2017-03-04</date><num>251</num></data>
<data><date>2017-03-04</date><num>519</num></data>
<data><date>2017-03-04</date><num>554</num></data>
<data><date>2017-03-04</date><num>616</num></data>
<data><date>2017-03-04</date><num>717</num></data>
<data><date>2017-03-04</date><num>163</num></data>
<data><date>2017-03-04</date><num>769</num></data>
<data><date>2017-03-04</date><num>626</num></data>
<data><date>2017-03-04</date><num>264</num></data>
<data><date>2017-03-04</date><num>55</num></data>
<data><date>2017-03-04</date><num>206</num></data>
<data><date>2017-03-04</date><num>419</num></data>
<data><date>2017-03-04</date><num>415</num></data>
<data><date>2017-03-04</date><num>301</num></data>
<data><date>2017-03-04</date><num>715</num></data>
<data><date>2017-03-04</date><num>32</num></data>
<data><date>2017-03-04</date><num>121</num></data>
<data><date>2017-03-04</date><num>821</num></data>
<data><date>2017-03-04</date><num>981</num></data>
<data><date>2017-03-04</date><num>177</num></data>
<data><date>2017-03-04</date><num>744</num></data>
<data><date>2017-03-04</date><num>957</num></data>
<data><date>2017-03-04</date><num>591</num></data>
<data><date>2017-03-04</date><num>655</num></data>
<data><date>2017-03-04</date><num>22</num></data>
<data><date>2017-03-04</date><num>413</num></data>
<data><date>2017-03-04</date><num>455</num></data>
<data><date>2017-03-04</date><num>121</num></data>
<data><date>2017-03-04</date><num>150</num></data>
<data><date>2017-03-04</date><num>395</num></data>
<data><date>2017-03-04</date><num>835</num></data>
<data><date>2017-03-04</date><num>400</num></data>
<data><date>2017-03-04</date><num>913</num></data>
<data><date>2017-03-04</date><num>389</num></data>
<data><date>2017-03-04</date><num>16</num></data>
<data><date>2017-03-04</date><num>629</num></data>
<data><date>2017-03-04</date><num>551</num></data>
<data><date>2017-03-04</date><num>784</num></data>
<data><date>2017-03-04</date><num>255</num></data>
<data><date>2017-03-04</date><num>815</num></data>
<data><date>2017-03-04</date><num>838</num></data>
<data><date>2017-03-04</date><num>460</num></data>
<data><date>2017-03-04</date><num>233</num></data>
<data><date>2017-03-04</date><num>253</num></data>
<data><date>2017-03-04</date><num>760</num></data>
<data><date>2017-03-04</date><num>947</num></data>
<data><date>2017-03-04</date><num>285</num></data>
<data><date>2017-03-04</date><num>880</num></data>
<data><date>2017-03-04</date><num>768</num></data>
<data><date>2017-03-04</date><num>265</num></data>
<data><date>2017-03-04</date><num>57</num></data>
<data><date>2017-03-04</date><num>512</num></data>
<data><date>2017-03-04</date><num>221</num></data>
<data><date>2017-03-04</date><num>647</num></data>
<data><date>2017-03-04</date><num>166</num></data>
<data><date>2017-03-04</date><num>243</num></data>
<data><date>2017-03-04</date><num>59</num></data>
<data><date>2017-03-04</date><num>621</num></data>
<data><date>2017-03-04</date><num>364</num></data>
<data><date>2017-03-04</date><num>209</num></data>
<data><date>2017-03-04</date><num>16</num></data>
<data><date>2017-03-04</date><num>198</num></data>
<data><date>2017-03-04</date><num>609</num></data>
<data><date>2017-03-04</date><num>928</num></data>
<data><date>2017-03-04</date><num>586</num></data>
<data><date>2017-03-04</date><num>624</num></data>
<data><date>2017-03-04</date><num>557</num></data>
<data><date>2017-03-04</date><num>137</num></data>
<data><date>2017-03-04</date><num>408</num></data>
<data><date>2017-03-04</date><num>811</num></data>
<data><date>2017-03-04</date><num>951</num></data>
<data><date>2017-03-04</date><num>245</num></data>
<data><date>2017-03-04</date><num>271</num></data>
<data><date>2017-03-04</date><num>184</num></data>
<data><date>2017-03-04</date><num>498</num></data>
<data><date>2017-03-04</date><num>30</num></data>
<data><date>2017-03-04</date><num>131</num></data>
<data><date>2017-03-04</date><num>782</num></data>
<data><date>2017-03-04</date><num>910</num></data>
<data><date>2017-03-04</date><num>899</num></data>
<data><date>2017-03-04</date><num>47</num></data>
<data><date>2017-03-04</date><num>967</num></data>
<data><date>2017-03-04</date><num>411</num></data>
<data><date>2017-03-04</date><num>267</num></data>
<data><date>2017-03-04</date><num>613</num></data>
<data><date>2017-03-04</date><num>577</num></data>
<data><date>2017-03-04</date><num>510</num></data>
<data><date>2017-03-04</date><num>672</num></data>
<data><date>2017-03-04</date><num>198</num></data>
<data><date>2017-03-04</date><num>873</num></data>
<data><date>2017-03-04</date><num>881</num></data>
<data><date>2017-03-04</date><num>213</num></data>
<data><date>2017-03-04</date><num>70</num></data>
<data><date>2017-03-04</date><num>490</num></data>
<data><date>2017-03-04</date><num>141</num></data>
<data><date>2017-03-04</date><num>656</num></data>
<data><date>2017-03-04</date><num>113</num></data>
<data><date>2017-03-04</date><num>697</num></data>
<data><date>2017-03-04</date><num>793</num></data>
<data><date>2017-03-04</date><num>521</num></data>
<data><date>2017-03-04</date><num>508</num></data>
<data><date>2017-03-04</date><num>744</num></data>
<data><date>2017-03-04</date><num>765</num></data>
<data><date>2017-03-04</date><num>778</num></data>
<data><date>2017-03-04</date><num>927</num></data>
<data><date>2017-03-04</date><num>263</num></data>
<data><date>2017-03-04</date><num>808</num></data>
<data><date>2017-03-04</date><num>58</num></data>
<data><date>2017-03-04</date><num>45</num></data>
<data><date>2017-03-04</date><num>717</num></data>
<data><date>2017-03-04</date><num>957</num></data>
<data><date>2017-03-04</date><num>91</num></data>
<data><date>2017-03-04</date><num>683</num></data>
<data><date>2017-03-04</date><num>367</num></data>
<data><date>2017-03-04</date><num>358</num></data>
<data><date>2017-03-04</date><num>296</num></data>
<data><date>2017-03-04</date><num>943</num></data>
<data><date>2017-03-04</date><num>867</num></data>
<data><date>2017-03-04</date><num>968</num></data>
<data><date>2017-03-04</date><num>140</num></data>
<data><date>2017-03-04</date><num>739</num></data>
<data><date>2017-03-04</date><num>848</num></data>
<data><date>2017-03-04</date><num>353</num></data>
<data><date>2017-03-04</date><num>809</num></data>
<data><date>2017-03-04</date><num>337</num></data>
<data><date>2017-03-04</date><num>493</num></data>
<data><date>2017-03-04</date><num>465</num></data>
<data><date>2017-03-04</date><num>450</num></data>
<data><date>2017-03-04</date><num>189</num></data>
<data><date>2017-03-04</date><num>257</num></data>
<data><date>2017-03-04</date><num>970</num></data>
<data><date>2017-03-04</date><num>697</num></data>
<data><date>2017-03-04</date><num>1000</num></data>
<data><date>2017-03-04</date><num>735</num></data>
<data><date>2017-03-04</date><num>474</num></data>
<data><date>2017-03-04</date><num>927</num></data>
<data><date>2017-03-04</date><num>998</num></data>
<data><date>2017-03-04</date><num>281</num></data>
<data><date>2017-03-04</date><num>985</num></data>
<data><date>2017-03-04</date><num>42</num></data>
<data><date>2017-03-04</date><num>998</num></data>
<data><date>2017-03-04</date><num>941</num></data>
<data><date>2017-03-04</date><num>132</num></data>
<data><date>2017-03-04</date><num>681</num></data>
<data><date>2017-03-04</date><num>307</num></data>
<data><date>2017-03-04</date><num>489</num></data>
<data><date>2017-03-04</date><num>976</num></data>
<data><date>2017-03-04</date><num>250</num></data>
<data><date>2017-03-04</date><num>355</num></data>
<data><date>2017-03-04</date><num>944</num></data>
<data><date>2017-03-04</date><num>390</num></data>
<data><date>2017-03-04</date><num>94</num></data>
<data><date>2017-03-04</date><num>791</num></data>
<data><date>2017-03-04</date><num>742</num></data>
<data><date>2017-03-04</date><num>903</num></data>
<data><date>2017-03-04</date><num>128</num></data>
<data><date>2017-03-04</date><num>234</num></data>
<data><date>2017-03-04</date><num>367</num></data>
<data><date>2017-03-04</date><num>578</num></data>
</res>